setup.py
shikher_probability/Binomialdistribution.py
shikher_probability/Gaussiandistribution.py
shikher_probability/Generaldistribution.py
shikher_probability/__init__.py
shikher_probability.egg-info/PKG-INFO
shikher_probability.egg-info/SOURCES.txt
shikher_probability.egg-info/dependency_links.txt
shikher_probability.egg-info/not-zip-safe
shikher_probability.egg-info/top_level.txt