Metadata-Version: 1.0
Name: shikher-probability
Version: 1.0
Summary: Gaussian  and Binomial distributions
Home-page: UNKNOWN
Author: Shikher Srivastava
Author-email: shikher707@gmail.com
License: UNKNOWN
Platform: UNKNOWN
